{
    "waves": [
      {
        "final x": 50,
        "final y": 50,
        "number of chicken": 14,
        "number of chicken per row": 14,
        "type": "red chicken",
        "initial y": 50,
        "initial x": 1000,
        "hidden":"right"
      },
      {
        "final x": 80,
        "final y": 75,
        "number of chicken": 13,
        "number of chicken per row": 13,
        "type": "green chicken",
        "initial y": 75,
        "initial x": -1000,
        "hidden":"left"
      },
      {
        "final x": 50,
        "final y": 100,
        "number of chicken": 14,
        "number of chicken per row": 14,
        "type": "red chicken",
        "initial y": 100,
        "initial x": 1000,
        "hidden":"right"
      },
      {
        "final x": 80,
        "final y": 125,
        "number of chicken": 13,
        "number of chicken per row": 13,
        "type": "green chicken",
        "initial y": 125,
        "initial x": -1000,
        "hidden":"left"
      },
      {
      "type": "boss",
      "final x":600,
      "final y":200,
      "initial y": -200,
      "initial x": 600,
      "hidden":"up"
      }
    ]
  }
  